6_rosdep-0.1.0.dist-info/DESCRIPTION.rst
6_rosdep-0.1.0.dist-info/METADATA
6_rosdep-0.1.0.dist-info/RECORD
6_rosdep-0.1.0.dist-info/WHEEL
6_rosdep-0.1.0.dist-info/entry_points.txt
6_rosdep-0.1.0.dist-info/metadata.json
6_rosdep-0.1.0.dist-info/top_level.txt
fixed_rosdep/__init__.py
fixed_rosdep/_version.py
fixed_rosdep/cache_tools.py
fixed_rosdep/catkin_packages.py
fixed_rosdep/catkin_support.py
fixed_rosdep/core.py
fixed_rosdep/dependency_graph.py
fixed_rosdep/gbpdistro_support.py
fixed_rosdep/install.py
fixed_rosdep/installers.py
fixed_rosdep/loader.py
fixed_rosdep/lookup.py
fixed_rosdep/main.py
fixed_rosdep/meta.py
fixed_rosdep/model.py
fixed_rosdep/rep3.py
fixed_rosdep/rosdistrohelper.py
fixed_rosdep/rospack.py
fixed_rosdep/rospkg_loader.py
fixed_rosdep/shell_utils.py
fixed_rosdep/sources_list.py
fixed_rosdep/ament_packages/__init__.py
fixed_rosdep/ament_packages/constants.py
fixed_rosdep/ament_packages/packages.py
fixed_rosdep/ament_packages/resources.py
fixed_rosdep/ament_packages/search_paths.py
fixed_rosdep/hello/__init__.py
fixed_rosdep/hello/main.py
fixed_rosdep/platforms/__init__.py
fixed_rosdep/platforms/alpine.py
fixed_rosdep/platforms/arch.py
fixed_rosdep/platforms/cygwin.py
fixed_rosdep/platforms/debian.py
fixed_rosdep/platforms/freebsd.py
fixed_rosdep/platforms/gem.py
fixed_rosdep/platforms/gentoo.py
fixed_rosdep/platforms/nix.py
fixed_rosdep/platforms/npm.py
fixed_rosdep/platforms/openembedded.py
fixed_rosdep/platforms/opensuse.py
fixed_rosdep/platforms/osx.py
fixed_rosdep/platforms/pip.py
fixed_rosdep/platforms/redhat.py
fixed_rosdep/platforms/slackware.py
fixed_rosdep/platforms/source.py
