Metadata-Version: 2.0
Name: 6-rosdep
Version: 0.1.0
Summary: we need rosdep
Home-page: https://github.com/6-robot/6-rosdep
Author: Wanjie Zhang
Author-email: zhangwanjie@6-robot.com
License: BSD
Platform: UNKNOWN
Requires-Dist: PyYAML (>=3.1)
Requires-Dist: catkin-pkg (>=0.4.0)
Requires-Dist: rosdistro (>=0.7.5)
Requires-Dist: rospkg (>=1.3.0)
